pyrew.py
pyrew-0.24.7.1.data/scripts/pyrew.py
pyrew-0.24.7.1.dist-info/METADATA
pyrew-0.24.7.1.dist-info/WHEEL
pyrew-0.24.7.1.dist-info/top_level.txt
pyrew-0.24.7.1.dist-info/RECORD
