Metadata-Version: 2.1
Name: pyrew
Version: 0.24.7.1
Summary: A Python library for writing shorter and more efficient Python code.
Home-page: https://github.com/AquaQuokka/pyrew
Author: AquaQuokka
License: BSD-3-Clause
Requires-Dist: humanize
Requires-Dist: pillow
Requires-Dist: flask
Requires-Dist: requests
Requires-Dist: jinja2
Requires-Dist: art
Requires-Dist: opencv-python
